LICENSE
MANIFEST.in
README.rst
setup.py
django_schema/__init__.py
django_schema/admin.py
django_schema/apps.py
django_schema/models.py
django_schema/tests.py
django_schema/urls.py
django_schema/views.py
django_schema.egg-info/PKG-INFO
django_schema.egg-info/SOURCES.txt
django_schema.egg-info/dependency_links.txt
django_schema.egg-info/requires.txt
django_schema.egg-info/top_level.txt
django_schema/migrations/__init__.py
django_schema/static/django_schema/css/main.css
django_schema/static/django_schema/images/logo/company-logo.png
django_schema/static/django_schema/js/script.js
django_schema/templates/django_schema/generate-form.html
django_schema/templates/django_schema/local-installed-apps-list.html
django_schema/templates/django_schema/models-of-local-app.html
django_schema/templates/django_schema/schema_index.html
django_schema/templates/django_schema/base_templates/_base.html
django_schema/templates/django_schema/base_templates/_base_master.html
django_schema/templates/django_schema/base_templates/partials/_footer.html
django_schema/templates/django_schema/base_templates/partials/_header.html