Metadata-Version: 1.1
Name: django-schema
Version: 0.1
Summary: A simple Django app to generate form schema for django models related to django apps
Home-page: https://github.com/bkawan/django_schema/
Author: Bikesh Kawan
Author-email: bikeshkawang@gmail.com
License: BSD License
Platform: UNKNOWN
Classifier: Environment :: Web Environment
Classifier: Framework :: Django
Classifier: Framework :: Django :: 2.1
Classifier: Intended Audience :: Developers
Classifier: License :: OSI Approved :: BSD License
Classifier: Operating System :: OS Independent
Classifier: Programming Language :: Python
Classifier: Programming Language :: Python :: 3.5
Classifier: Programming Language :: Python :: 3.6
Classifier: Programming Language :: Python :: 3.7
Classifier: Topic :: Internet :: WWW/HTTP
